ftperiodogram/__init__.py
ftperiodogram/core.py
ftperiodogram/modeler.py
ftperiodogram/summations.py
ftperiodogram/template.py
ftperiodogram/utils.py
ftperiodogram/version.py
ftperiodogram/tests/__init__.py
ftperiodogram/tests/test_modeler.py
ftperiodogram/tests/test_slow_template_modeler.py
ftperiodogram/tests/test_summations.py
ftperiodogram/tests/test_template.py
ftperiodogram/tests/test_utils.py
ftperiodogram-1.0.0.dist-info/DESCRIPTION.rst
ftperiodogram-1.0.0.dist-info/METADATA
ftperiodogram-1.0.0.dist-info/RECORD
ftperiodogram-1.0.0.dist-info/WHEEL
ftperiodogram-1.0.0.dist-info/metadata.json
ftperiodogram-1.0.0.dist-info/top_level.txt
