Metadata-Version: 2.0
Name: ftperiodogram
Version: 1.0.0
Summary: ftperiodogram: NlogN periodic template fitting
Home-page: http://github.com/jakevdp/nfft/
Author: John Hoffman
Author-email: jah5@princeton.edu
License: MIT
Platform: OS Independent
Classifier: Development Status :: 4 - Beta
Classifier: Environment :: Console
Classifier: Intended Audience :: Science/Research
Classifier: License :: OSI Approved :: MIT License
Classifier: Natural Language :: English
Classifier: Programming Language :: Python :: 2.7
Classifier: Programming Language :: Python :: 3.5
Classifier: Programming Language :: Python :: 3.6
Requires: nfft
Requires: pytest
Requires: scipy
Requires: numpy
Requires-Dist: nfft
Requires-Dist: numpy
Requires-Dist: pytest
Requires-Dist: scipy
